setup.py
black_goat_client.egg-info/PKG-INFO
black_goat_client.egg-info/SOURCES.txt
black_goat_client.egg-info/dependency_links.txt
black_goat_client.egg-info/requires.txt
black_goat_client.egg-info/top_level.txt
goat/__init__.py