Metadata-Version: 1.0
Name: black-goat-client
Version: 0.2.6
Summary: Simple client for the BlackGoat API
Home-page: http://diging.github.io/black-goat/
Author: Erick Peirson
Author-email: erick.peirson@asu.edu
License: GNU GPL 3
Platform: UNKNOWN
